README.rst
setup.cfg
setup.py
seaborn/request_client/__init__.py
seaborn/request_client/api_call.py
seaborn/request_client/connection_basic.py
seaborn/request_client/connection_endpoint.py
seaborn/request_client/endpoint.py
seaborn/request_client/errors.py
seaborn/request_client/intellisense.py
seaborn/request_client/repr_wrapper.py
seaborn_request_client.egg-info/PKG-INFO
seaborn_request_client.egg-info/SOURCES.txt
seaborn_request_client.egg-info/dependency_links.txt
seaborn_request_client.egg-info/requires.txt
seaborn_request_client.egg-info/top_level.txt