Metadata-Version: 1.1
Name: seaborn-request-client
Version: 0.0.4
Summary: Request Client creates and maintains connections using the request library, but make each url endpoint a remoteprocedure call with the response content returned.  These function calls can made from a "connection" which hasa hierarchy of objects that mirrors the hierarchy of the API.
Home-page: https://github.com/SeabornGames/RequestClient
Author: Ben Christenson
Author-email: Python@BenChristenson.com
License: MIT License
Platform: UNKNOWN
Classifier: Intended Audience :: Developers
Classifier: Natural Language :: English
Classifier: License :: Other/Proprietary License
Classifier: Operating System :: POSIX :: Linux
Classifier: Programming Language :: Python
Classifier: Programming Language :: Python :: 2.7
